.DS_Store
barbeque/__init__.py
barbeque/anylink.py
barbeque/compat.py
barbeque/compressor.py
barbeque/context_processors.py
barbeque/encoders.py
barbeque/exporter.py
barbeque/filer.py
barbeque/files.py
barbeque/logging.py
barbeque/shortcuts.py
barbeque/testing.py
barbeque/validators.py
barbeque/cms/__init__.py
barbeque/cms/toolbar.py
barbeque/commands/__init__.py
barbeque/commands/base.py
barbeque/commands/imaging.py
barbeque/forms/__init__.py
barbeque/forms/mixins.py
barbeque/forms/renderer.py
barbeque/locale/de/LC_MESSAGES/django.mo
barbeque/locale/de/LC_MESSAGES/django.po
barbeque/management/__init__.py
barbeque/management/commands/__init__.py
barbeque/management/commands/create_error_pages.py
barbeque/management/commands/render_static_templates.py
barbeque/staticfiles/__init__.py
barbeque/staticfiles/css.py
barbeque/staticfiles/loader.py
barbeque/staticfiles/middleware.py
barbeque/staticfiles/storage.py
barbeque/templates/.DS_Store
barbeque/templates/barbeque/.DS_Store
barbeque/templates/barbeque/forms/.DS_Store
barbeque/templates/barbeque/forms/field/checkboxinput.html
barbeque/templates/barbeque/forms/field/checkboxselectmultiple.html
barbeque/templates/barbeque/forms/field/radioselect.html
barbeque/templates/barbeque/forms/field/selectdatewidget.html
barbeque/templates/barbeque/forms/layout/div.html
barbeque/templates/barbeque/forms/layout/div_formset.html
barbeque/templates/barbeque/forms/row/default.html
barbeque/templatetags/__init__.py
barbeque/templatetags/barbeque_tags.py
barbeque/templatetags/buildcompress.py
barbeque/views/__init__.py
barbeque/views/decorators.py
barbeque/views/generic.py
barbeque/views/mixins.py
barbeque/views/multiform.py
barbeque-1.8.2.dist-info/DESCRIPTION.rst
barbeque-1.8.2.dist-info/METADATA
barbeque-1.8.2.dist-info/RECORD
barbeque-1.8.2.dist-info/WHEEL
barbeque-1.8.2.dist-info/metadata.json
barbeque-1.8.2.dist-info/top_level.txt
