Metadata-Version: 2.0
Name: barbeque
Version: 1.8.2
Summary: Helper and tools collection
Home-page: http://github.com/moccu/barbeque/
Author: Moccu GmbH & Co. KG
Author-email: info@moccu.com
License: BSD
Platform: UNKNOWN
Classifier: Development Status :: 4 - Beta
Classifier: Environment :: Web Environment
Classifier: Intended Audience :: Developers
Classifier: License :: OSI Approved :: BSD License
Classifier: Operating System :: OS Independent
Classifier: Programming Language :: Python
Classifier: Topic :: Software Development :: Libraries :: Python Modules
Classifier: Programming Language :: Python :: 2
Classifier: Programming Language :: Python :: 2.7
Classifier: Programming Language :: Python :: 3
Classifier: Programming Language :: Python :: 3.4
Classifier: Programming Language :: Python :: 3.5
Classifier: Programming Language :: Python :: Implementation :: CPython
Classifier: Programming Language :: Python :: Implementation :: PyPy
Classifier: Framework :: Django
Requires-Dist: Django (>=1.8,<2.0)
Requires-Dist: python-dateutil (>=2.4.0)
Provides-Extra: docs
Requires-Dist: sphinx; extra == 'docs'
Requires-Dist: sphinx-rtd-theme; extra == 'docs'
Provides-Extra: exporter
Requires-Dist: openpyxl (>=2.4.8,<2.5); extra == 'exporter'
Provides-Extra: tests
Requires-Dist: Pillow (==4.2.1); extra == 'tests'
Requires-Dist: django-anylink (==0.4.2); extra == 'tests'
Requires-Dist: django-cms (==3.4.4); extra == 'tests'
Requires-Dist: django-compressor (==2.2); extra == 'tests'
Requires-Dist: django-filer (==1.2.8); extra == 'tests'
Requires-Dist: django-floppyforms (==1.7.0); extra == 'tests'
Requires-Dist: django-polymorphic (==1.3); extra == 'tests'
Requires-Dist: django-treebeard (==4.1.2); extra == 'tests'
Requires-Dist: easy-thumbnails (==2.4.1); extra == 'tests'
Requires-Dist: factory-boy (>=2.9.2); extra == 'tests'
Requires-Dist: mock (==2.0.0); extra == 'tests'
Requires-Dist: openpyxl (==2.4.8); extra == 'tests'
Requires-Dist: psutil (==5.3.0); extra == 'tests'
Requires-Dist: pytest (==3.2.1); extra == 'tests'
Requires-Dist: pytest-cov (==2.5.1); extra == 'tests'
Requires-Dist: pytest-django (==3.1.2); extra == 'tests'
Requires-Dist: pytest-flakes (==2.0.0); extra == 'tests'
Requires-Dist: pytest-isort (==0.1.0); extra == 'tests'
Requires-Dist: pytest-pep8 (==1.0.6); extra == 'tests'
Requires-Dist: tox (==2.8.1); extra == 'tests'
Requires-Dist: tox-pyenv (==1.1.0); extra == 'tests'
